simmes/GRB.py
simmes/PLOTS.py
simmes/RSP.py
simmes/SPECFUNC.py
simmes/__init__.py
simmes/bayesian_block.py
simmes/fluence.py
simmes/simulations.py
simmes/threshold_search.py
simmes/__pycache__/GRB.cpython-310.pyc
simmes/__pycache__/SPECFUNC.cpython-310.pyc
simmes/__pycache__/__init__.cpython-310.pyc
simmes/__pycache__/bayesian_block.cpython-310.pyc
simmes/unit_tests/__init__.py
simmes/unit_tests/test_class_SPECFUNC.py
simmes/unit_tests/test_package_bayesian_block.py
simmes/unit_tests/test_package_cosmology.py
simmes/unit_tests/test_package_det_ang_dependence.py
simmes/unit_tests/test_files/grb_130831A_1chan_1s.txt
simmes/unit_tests/test_files/grb_130831A_1chan_64ms.txt
simmes/unit_tests/test_files/grb_160314A_1chan_1s.txt
simmes/unit_tests/test_files/grb_160314A_1chan_64ms.txt
simmes/util_packages/.DS_Store
simmes/util_packages/__init__.py
simmes/util_packages/cosmology.py
simmes/util_packages/datatypes.py
simmes/util_packages/det_ang_dependence.py
simmes/util_packages/fluctuations.py
simmes/util_packages/globalconstants.py
simmes/util_packages/__pycache__/__init__.cpython-310.pyc
simmes/util_packages/__pycache__/cosmology.cpython-310.pyc
simmes/util_packages/__pycache__/globalconstants.cpython-310.pyc
simmes/util_packages/files-det-ang-dependence/gridnum_imx_imy.txt
simmes/util_packages/files-det-ang-dependence/pcode-imx-imy.dat
simmes/util_packages/files-det-ang-dependence/pcode-map.img
simmes/util_packages/files-spec-unc/bat-chan-sys-err-fracs.txt
simmes/util_packages/files-spec-unc/spec-unc-fit-params.txt
simmes/util_packages/files-swift-bat-resps/bat_grid_01.rsp
simmes/util_packages/files-swift-bat-resps/bat_grid_02.rsp
simmes/util_packages/files-swift-bat-resps/bat_grid_03.rsp
simmes/util_packages/files-swift-bat-resps/bat_grid_04.rsp
simmes/util_packages/files-swift-bat-resps/bat_grid_05.rsp
simmes/util_packages/files-swift-bat-resps/bat_grid_07.rsp
simmes/util_packages/files-swift-bat-resps/bat_grid_08.rsp
simmes-0.3.0.dist-info/licenses/LICENSE
simmes-0.3.0.dist-info/METADATA
simmes-0.3.0.dist-info/WHEEL
simmes-0.3.0.dist-info/top_level.txt
simmes-0.3.0.dist-info/RECORD
