Metadata-Version: 2.4
Name: simmes
Version: 0.3.0
Summary: GRB measurement simulation packages
Author-email: Michael Moss <mikejmoss3@gmail.com>
Project-URL: Repository, https://github.com/mikemoss3/simmes
Classifier: Intended Audience :: Science/Research
Classifier: Programming Language :: Python
Classifier: Programming Language :: Python :: 3
Classifier: Topic :: Scientific/Engineering :: Astronomy
Requires-Python: >=3.8
License-File: LICENSE
Requires-Dist: Numpy<2,>=1.26.4
Requires-Dist: Scipy>=1.14.0
Requires-Dist: Astropy>=6.1.2
Requires-Dist: Fitsio>=1.2.4
Dynamic: license-file
